topsis/__init__.py
topsis/topsis.py
Topsis_UditGupta_102203835-1.0.1.dist-info/LICENSE
Topsis_UditGupta_102203835-1.0.1.dist-info/METADATA
Topsis_UditGupta_102203835-1.0.1.dist-info/WHEEL
Topsis_UditGupta_102203835-1.0.1.dist-info/entry_points.txt
Topsis_UditGupta_102203835-1.0.1.dist-info/top_level.txt
Topsis_UditGupta_102203835-1.0.1.dist-info/RECORD
