Metadata-Version: 2.1
Name: Topsis-UditGupta-102203835
Version: 1.0.1
Summary: A Python package to perform TOPSIS (Technique for Order Preference by Similarity to Ideal Solution)
Home-page: https://github.com/uditgupta08/Topsis
Author: Udit Gupta
Author-email: udit0808gupta@gmail.com
Classifier: Programming Language :: Python :: 3
Classifier: License :: OSI Approved :: MIT License
Classifier: Operating System :: OS Independent
Requires-Python: >=3.6
License-File: LICENSE
Requires-Dist: numpy
Requires-Dist: pandas
